wiktionary_fetcher/__init__.py
wiktionary_fetcher/__main__.py
wiktionary_fetcher/py.typed
wiktionary_term_fetcher-0.1.1.dist-info/LICENSE
wiktionary_term_fetcher-0.1.1.dist-info/METADATA
wiktionary_term_fetcher-0.1.1.dist-info/WHEEL
wiktionary_term_fetcher-0.1.1.dist-info/entry_points.txt
wiktionary_term_fetcher-0.1.1.dist-info/top_level.txt
wiktionary_term_fetcher-0.1.1.dist-info/RECORD
